odoo/addons/account_invoice_line_complimentary/README.rst
odoo/addons/account_invoice_line_complimentary/__init__.py
odoo/addons/account_invoice_line_complimentary/__manifest__.py
odoo/addons/account_invoice_line_complimentary/i18n/it.po
odoo/addons/account_invoice_line_complimentary/models/__init__.py
odoo/addons/account_invoice_line_complimentary/models/account_invoice.py
odoo/addons/account_invoice_line_complimentary/models/account_invoice_line.py
odoo/addons/account_invoice_line_complimentary/models/res_company.py
odoo/addons/account_invoice_line_complimentary/models/res_config_settings.py
odoo/addons/account_invoice_line_complimentary/readme/CONFIGURE.rst
odoo/addons/account_invoice_line_complimentary/readme/CONTRIBUTORS.rst
odoo/addons/account_invoice_line_complimentary/readme/DESCRIPTION.rst
odoo/addons/account_invoice_line_complimentary/readme/USAGE.rst
odoo/addons/account_invoice_line_complimentary/static/description/icon.png
odoo/addons/account_invoice_line_complimentary/static/description/index.html
odoo/addons/account_invoice_line_complimentary/tests/__init__.py
odoo/addons/account_invoice_line_complimentary/tests/common.py
odoo/addons/account_invoice_line_complimentary/tests/test_complimentary.py
odoo/addons/account_invoice_line_complimentary/views/account_invoice_line_views.xml
odoo/addons/account_invoice_line_complimentary/views/account_invoice_views.xml
odoo/addons/account_invoice_line_complimentary/views/res_config_settings_views.xml
odoo12_addon_account_invoice_line_complimentary-12.0.1.0.0.99.dev1.dist-info/METADATA
odoo12_addon_account_invoice_line_complimentary-12.0.1.0.0.99.dev1.dist-info/WHEEL
odoo12_addon_account_invoice_line_complimentary-12.0.1.0.0.99.dev1.dist-info/top_level.txt
odoo12_addon_account_invoice_line_complimentary-12.0.1.0.0.99.dev1.dist-info/RECORD
